Stoplight.v
//==============================================================================
// Stoplight Module for Lab 4
//
// Note on lights:
// 	Each bit represents the on/off signal for a light.
// 	Bit | Light
// 	------------
// 	0   | Red
// 	1   | Yellow
// 	2   | Green
//==============================================================================

module Stoplight(
	input            clk,         // Clock signal
	input            rst,         // Reset signal for FSM
	input            car_present, // Is there a car on Prospect?
	output reg [2:0] light_pros,  // Prospect Avenue Light
	output reg [2:0] light_wash   // Washington Road Light
);

	// Declare Local Vars Here
	reg [3:0] state;
	reg [3:0] next_state;
	// ...

	// Declare State Names Here
	localparam INIT = 4'd0;
	localparam WCYCLE1 = 4'd1;
	localparam WCYCLE2 = 4'd2;
	localparam WCYCLE3 = 4'd3;
	localparam WCYCLE4 = 4'd4;
	localparam W_to_P = 4'd5;
	localparam PCYCLE1 = 4'd6;
	localparam PCYCLE2 = 4'd7;
	localparam PCYCLE3 = 4'd8;
	localparam PCYCLE4 = 4'd9;
	localparam P_to_W = 4'd10;

	// Light Colors
	localparam RED = 3'b001;
	localparam YLW = 3'b010;
	localparam GRN = 3'b100;

	// Output Combinational Logic
	always @( * ) begin
		light_pros = 3'b000;
		light_wash = 3'b000;

		if (state == INIT) begin
			light_wash = GRN;
			light_pros = RED;
		end
		// Write your output logic here
		else if (state == WCYCLE1 || state == WCYCLE2 || state == WCYCLE3 || state == WCYCLE4) begin
			light_wash = GRN;
			light_pros = RED;
		end

		else if (state == PCYCLE1 || state == PCYCLE2 || state == PCYCLE3 || state == PCYCLE4) begin
			light_wash = RED;
			light_pros = GRN;
		end

		else if (state == W_to_P) begin
			light_wash = YLW;
			light_pros = RED;
		end

		else if (state == P_to_W) begin
			light_wash = RED;
			light_pros = YLW;
		end
	end

	// Next State Combinational Logic
	always @( * ) begin
		// Write your Next State Logic Here
		next_state = state; // avoid implicit latching
		if (state == INIT) begin
			next_state = WCYCLE2;
		end
		else if (state == WCYCLE2) begin
			next_state = WCYCLE3;
		end
		else if (state == WCYCLE3) begin
			next_state = WCYCLE4;
		end
		else if (state == WCYCLE4) begin
			if (car_present) next_state = W_to_P;
			else next_state = WCYCLE4;
		end
		else if (state == W_to_P) begin
			next_state = PCYCLE1;
		end
		else if (state == PCYCLE1) begin
			next_state = PCYCLE2;
		end
		else if (state == PCYCLE2) begin
			next_state = PCYCLE3;
		end
		else if (state == PCYCLE3) begin
			next_state = PCYCLE4;
		end
		else if (state == PCYCLE4) begin
			next_state = P_to_W;
		end
		else if (state == P_to_W) begin
			next_state = WCYCLE1;
		end
		else if (state == WCYCLE1) begin
			next_state = WCYCLE2;
		end
	end

	// State Update Sequential Logic
	always @(posedge clk) begin
		if (rst) begin
			// Update state to reset state
			state <= INIT;
		end
		else begin
			// Update state to next state
			state <= next_state;
		end
	end

endmodule

Stoplight.t.v
//==============================================================================
// Stoplight Testbench Module for Lab 4
//==============================================================================
`timescale 1ns/100ps

`include "Stoplight.v"

module StoplightTest;

	// Local Vars
	reg clk = 1;
	reg rst = 0;
	reg car = 0;
	wire [2:0] lp, lw;

	// Light Colors
	localparam GRN = 3'b100;
	localparam YLW = 3'b010;
	localparam RED = 3'b001;

	// VCD Dump
	initial begin
		$dumpfile("StoplightTest.vcd");
		$dumpvars;
	end

	// Stoplight Module
	Stoplight light(
		.clk        (clk),
		.rst        (rst),
		.car_present(car),
		.light_pros (lp),
		.light_wash (lw)
	);

	// Clock
	always begin
		#2.5 clk = ~clk;
	end

	// Main Test Logic
	initial begin
		// Write your set of test cases here
		#1
		rst = 1;
		#5 // t = 6
		rst = 0;
		#1
		if (lp !== RED || lw !== GRN) begin
			$display("Error at time %t", $time);
		end
		#34 // t = 41
		car = 1;
		#1 
		if (lp !== RED || lw !== GRN) begin
			$display("Error at time %t", $time);
		end
		#4 // t = 46
		#1
		if (lp !== RED || lw !== YLW) begin
			$display("Error at time %t", $time);
		end
		#4 // t = 51
		car = 0;
		#1
		if (lp !== GRN || lw !== RED) begin
			$display("Error at time %t", $time);
		end
		#14 // t = 66
		car = 1;
		#1
		if (lp !== GRN || lw !== RED) begin
			$display("Error at time %t", $time);
		end
		#4 // t = 71
		#1
		if (lp !== YLW || lw !== RED) begin
			$display("Error at time %t", $time);
		end
		#4 // t = 76
		#1 
		if (lp !== RED || lw !== GRN) begin
			$display("Error at time %t", $time);
		end
		#9 // t = 86
		car = 0;
		#1 
		if (lp !== RED || lw !== GRN) begin
			$display("Error at time %t", $time);
		end
		#19 // t = 106
		car = 1;
		#1
		if (lp !== RED || lw !== GRN) begin
			$display("Error at time %t", $time);
		end
		#9 // t = 116
		car = 0;
		#1
		if (lp !== GRN || lw !== RED) begin
			$display("Error at time %t", $time);
		end
		#14 // t = 131
		car = 1;
		#1
		if (lp !== GRN || lw !== RED) begin
			$display("Error at time %t", $time);
		end
		#4 // t = 136
		car = 0;
		#1
		if (lp !== YLW || lw !== RED) begin
			$display("Error at time %t", $time);
		end
		#3 // t = 140
		$finish;
	end

endmodule

StoplightTest.vcd
$date
	Thu Oct 21 18:41:12 2021
$end
$version
	Icarus Verilog
$end
$timescale
	100ps
$end
$scope module StoplightTest $end
$var wire 3 ! lw [2:0] $end
$var wire 3 " lp [2:0] $end
$var reg 1 # car $end
$var reg 1 $ clk $end
$var reg 1 % rst $end
$scope module light $end
$var wire 1 # car_present $end
$var wire 1 $ clk $end
$var wire 1 % rst $end
$var reg 3 & light_pros [2:0] $end
$var reg 3 ' light_wash [2:0] $end
$var reg 4 ( next_state [3:0] $end
$var reg 4 ) state [3:0] $end
$upscope $end
$upscope $end
$enddefinitions $end
#0
$dumpvars
bx )
bx (
bx '
bx &
0%
1$
0#
bx "
bx !
$end
#10
1%
#25
0$
#50
b10 (
b100 !
b100 '
b1 "
b1 &
b0 )
1$
#60
0%
#75
0$
#100
b11 (
b100 !
b100 '
b1 "
b1 &
b10 )
1$
#125
0$
#150
b100 (
b100 !
b100 '
b1 "
b1 &
b11 )
1$
#175
0$
#200
b100 !
b100 '
b1 "
b1 &
b100 )
1$
#225
0$
#250
1$
#275
0$
#300
1$
#325
0$
#350
1$
#375
0$
#400
1$
#410
b101 (
1#
#425
0$
#450
b110 (
b10 !
b10 '
b1 "
b1 &
b101 )
1$
#475
0$
#500
b111 (
b1 !
b1 '
b100 "
b100 &
b110 )
1$
#510
b111 (
0#
#525
0$
#550
b1000 (
b1 !
b1 '
b100 "
b100 &
b111 )
1$
#575
0$
#600
b1001 (
b1 !
b1 '
b100 "
b100 &
b1000 )
1$
#625
0$
#650
b1010 (
b1 !
b1 '
b100 "
b100 &
b1001 )
1$
#660
b1010 (
1#
#675
0$
#700
b1 (
b1 !
b1 '
b10 "
b10 &
b1010 )
1$
#725
0$
#750
b10 (
b100 !
b100 '
b1 "
b1 &
b1 )
1$
#775
0$
#800
b11 (
b100 !
b100 '
b1 "
b1 &
b10 )
1$
#825
0$
#850
b100 (
b100 !
b100 '
b1 "
b1 &
b11 )
1$
#860
b100 (
0#
#875
0$
#900
b100 !
b100 '
b1 "
b1 &
b100 )
1$
#925
0$
#950
1$
#975
0$
#1000
1$
#1025
0$
#1050
1$
#1060
b101 (
1#
#1075
0$
#1100
b110 (
b10 !
b10 '
b1 "
b1 &
b101 )
1$
#1125
0$
#1150
b111 (
b1 !
b1 '
b100 "
b100 &
b110 )
1$
#1160
b111 (
0#
#1175
0$
#1200
b1000 (
b1 !
b1 '
b100 "
b100 &
b111 )
1$
#1225
0$
#1250
b1001 (
b1 !
b1 '
b100 "
b100 &
b1000 )
1$
#1275
0$
#1300
b1010 (
b1 !
b1 '
b100 "
b100 &
b1001 )
1$
#1310
b1010 (
1#
#1325
0$
#1350
b1 (
b1 !
b1 '
b10 "
b10 &
b1010 )
1$
#1360
b1 (
0#
#1375
0$
#1400
b10 (
b100 !
b100 '
b1 "
b1 &
b1 )
1$
